mtailf
