Metadata-Version: 1.0
Name: mtailf
Version: 0.0.2
Summary: use tail -f to multiple remote server
Home-page: UNKNOWN
Author: skyleft
Author-email: im@andy-cheung.me
License: MIT License
Keywords: multiple tail,remote tail,tail
Platform: any
